LICENSE.txt
README
setup.cfg
setup.py
lairucrem/__init__.py
lairucrem/__main__.py
lairucrem/commands.py
lairucrem/config.py
lairucrem/controler.py
lairucrem/exceptions.py
lairucrem/extension.py
lairucrem/main_trio.py
lairucrem/mixin.py
lairucrem/patch_urwid.py
lairucrem/process.py
lairucrem/test.py
lairucrem/utils.py
lairucrem.egg-info/PKG-INFO
lairucrem.egg-info/SOURCES.txt
lairucrem.egg-info/dependency_links.txt
lairucrem.egg-info/entry_points.txt
lairucrem.egg-info/requires.txt
lairucrem.egg-info/top_level.txt
lairucrem/widgets/__init__.py
lairucrem/widgets/dialog.py
lairucrem/widgets/mainwidget.py
lairucrem/widgets/utils.py