Metadata-Version: 2.1
Name: lairucrem
Version: 5.3.2
Summary: A simple and powerful text-based interactive user interface for Mercurial
Home-page: http://hg.sr.ht/~alainl/lairucrem
Author: Alain Leufroy
Author-email: Alain Leufroy <alain.leufroy@gmail.com>
License: WTFPL, version 2
Download-URL: https://hg.sr.ht/~alainl/lairucrem/archive/5.3.2.tar.gz
Keywords: dvcs,mercurial,UI,interactive,console
Platform: UNKNOWN
Classifier: Environment :: Console :: Curses
Classifier: License :: Freely Distributable
Classifier: Topic :: Software Development :: Version Control
Classifier: Topic :: Software Development :: User Interfaces
Classifier: Topic :: Utilities
License-File: LICENSE.txt
